PyClinet/Encryption.py
PyClinet/__init__.py
PyClinet/client.py
PyClinet-2.0.0.dist-info/LICENCE
PyClinet-2.0.0.dist-info/METADATA
PyClinet-2.0.0.dist-info/WHEEL
PyClinet-2.0.0.dist-info/top_level.txt
PyClinet-2.0.0.dist-info/RECORD
